citrination/__init__.py
citrination/__main__.py
citrination/command_router.py
citrination/util.py
citrination/commands/__init__.py
citrination/commands/create_dataset.py
citrination/commands/create_dataset_version.py
citrination/commands/get_file.py
citrination/commands/get_files.py
citrination/commands/get_pif.py
citrination/commands/update_dataset.py
citrination/commands/upload.py
citrination-1.1.1.dist-info/DESCRIPTION.rst
citrination-1.1.1.dist-info/METADATA
citrination-1.1.1.dist-info/RECORD
citrination-1.1.1.dist-info/WHEEL
citrination-1.1.1.dist-info/entry_points.txt
citrination-1.1.1.dist-info/metadata.json
citrination-1.1.1.dist-info/top_level.txt
